<?xml version='1.0' encoding='UTF-8'?>
<?artifactRepository version='1.1.0'?>
<artifacts size='1'>
  <artifact classifier='org.eclipse.update.feature' id='jp.pizzafactory.jre.x86.win32.win32' version='1.8.65.R20160120-0350'>
    <properties size='6'>
      <property name='artifact.size' value='62146123'/>
      <property name='download.size' value='62146123'/>
      <property name='maven-groupId' value='jp.pizzafactory.jre'/>
      <property name='maven-artifactId' value='jp.pizzafactory.jre.x86.win32.win32'/>
      <property name='maven-version' value='1.8.65-SNAPSHOT'/>
      <property name='download.contentType' value='application/zip'/>
    </properties>
  </artifact>
</artifacts>
